akita/.DS_Store
akita/__init__.py
akita/__main__.py
akita/api/__init__.py
akita/api/base_ai_provider.py
akita/api/config.toml
akita/api/google_genai_provider.py
akita/api/openai_provider.py
akita/api/provider_factory.py
akita/api/utils/config_loader.py
akita/api/utils/utils.py
akita/assistant/.DS_Store
akita/assistant/.chainlit/config.toml
akita/assistant/.chainlit/translations/en-US.json
akita/assistant/.chainlit/translations/pt-BR.json
akita/assistant/__init__.py
akita/assistant/app.py
akita/assistant/app_terminal.py
akita/assistant/chainlit.md
akita/assistant/config.py
akita/assistant/database.py
akita/assistant/document_loader.py
akita/assistant/public/.DS_Store
akita/assistant/public/favicon.png
akita/assistant/public/logo_dark.png
akita/assistant/public/logo_light.png
akita/assistant/rag_chain.py
akita/assistant/run.py
akita/assistant/text_splitter.py
akita/cli/.DS_Store
akita/cli/__init__.py
akita/cli/cli.py
akita/cli/command_factory.py
akita/cli/commands/.DS_Store
akita/cli/commands/__init__.py
akita/cli/commands/add_command.py
akita/cli/commands/assistant_command.py
akita/cli/commands/base_command.py
akita/cli/commands/describe_command.py
akita/cli/commands/init_command.py
akita/cli/commands/readme_command.py
akita/cli/commands/remove_command.py
akita/cli/commands/review_command.py
akita/cli/commands/show_command.py
akita/cli/config.py
akita/cli/main_parser.py
akita/cli/plugin_manager.py
akita/plugins/.DS_Store
akita/plugins/__init__.py
akita/plugins/base_plugin.py
akita/plugins/git/.DS_Store
akita/plugins/git/__init__.py
akita/plugins/git/commands/__init__.py
akita/plugins/git/commands/git_add_command.py
akita/plugins/git/commands/git_commit_command.py
akita/plugins/git/git_plugin.py
akita/plugins/git/utils/__init__.py
akita/plugins/git/utils/utils.py
akita/plugins/template/__init__.py
akita/plugins/template/commands/__init__.py
akita/plugins/template/commands/template_dummy_command.py
akita/plugins/template/template_plugin.py
akita/services/.DS_Store
akita_ai-0.1.200.dist-info/LICENSE
akita_ai-0.1.200.dist-info/METADATA
akita_ai-0.1.200.dist-info/WHEEL
akita_ai-0.1.200.dist-info/entry_points.txt
akita_ai-0.1.200.dist-info/RECORD
