Metadata-Version: 2.1
Name: akita-ai
Version: 0.1.200
Summary: AI-enhanced development tool.
Home-page: https://akita.ai
License: Apache-2.0
Author: Gauthier Piarrette
Author-email: gauthier@akita.ai
Requires-Python: >=3.9,<4.0
Classifier: Development Status :: 4 - Beta
Classifier: Intended Audience :: Developers
Classifier: License :: OSI Approved :: Apache Software License
Classifier: Operating System :: OS Independent
Classifier: Programming Language :: Python :: 3
Classifier: Programming Language :: Python :: 3.9
Classifier: Programming Language :: Python :: 3.10
Classifier: Programming Language :: Python :: 3.11
Classifier: Programming Language :: Python :: 3.12
Requires-Dist: chainlit (==1.0.0)
Requires-Dist: chardet (==5.1.0)
Requires-Dist: chromadb (==0.4.23)
Requires-Dist: google-generativeai (>=0.5.2,<0.6.0)
Requires-Dist: langchain (==0.1.9)
Requires-Dist: langchain-community (==0.0.24)
Requires-Dist: langchain-core (==0.1.45)
Requires-Dist: langchain-google-genai (>=1.0.3,<2.0.0)
Requires-Dist: langchain-openai (==0.0.7)
Requires-Dist: onnxruntime (==1.16.0)
Requires-Dist: openai (==1.10.0)
Requires-Dist: prompt-toolkit (==3.0.43)
Requires-Dist: rich (==12.6.0)
Requires-Dist: tiktoken (==0.6.0)
Requires-Dist: tree-sitter (==0.20.4)
Requires-Dist: tree-sitter-languages (==1.10.2)
Project-URL: Documentation, https://github.com/gauthierpiarrette/akita-ai
Project-URL: Repository, https://github.com/gauthierpiarrette/akita-ai
